setup.py
vboxoverlord/__init__.py
vboxoverlord/commands.py
vboxoverlord/util.py
vboxoverlord/vbox.py
vboxoverlord.egg-info/PKG-INFO
vboxoverlord.egg-info/SOURCES.txt
vboxoverlord.egg-info/dependency_links.txt
vboxoverlord.egg-info/entry_points.txt
vboxoverlord.egg-info/not-zip-safe
vboxoverlord.egg-info/requires.txt
vboxoverlord.egg-info/top_level.txt