Metadata-Version: 1.1
Name: vboxoverlord
Version: 0.2.2
Summary: Overlord of all things virtualbox
Home-page: https://github.com/rossdylan/vbox-overlord
Author: Ross Delinger
Author-email: rossdylan@csh.rit.edu
License: MIT
Platform: UNKNOWN
Classifier: Programming Language :: Python :: 2
